{
  "version": 1,
  "set": "95",
  "mapping": {
    "UDNqZ4fXXj": "q20",
    "ov5oeNY4P4": "q12",
    "bAsMvmt2uq": "q3",
    "dMVGGk3dC9": "q2",
    "rwVMVL7DpS": "q28",
    "ku4c8kXBep": "q4",
    "bJiEpwGPsN": "q13",
    "FdrVVAbjmL": "q31",
    "Nz3uvU4wEs": "q10",
    "ecbu5ParY9": "q15",
    "UnXqAe6Cph": "q14",
    "r2YSeZiKz2": "q11",
    "26Rz2uSUXx": "q23",
    "FAgLSyzoRd": "q5",
    "vooNSEcDhu": "q17",
    "3FXJtg5J5o": "q1",
    "oUgAoQKTXE": "q29",
    "DxAMKS9vkc": "q6",
    "khTnGvcsfG": "q18",
    "EVxigTRo7b": "q7",
    "gPEfYs9CcH": "q24",
    "MK8fbnZuXb": "q22",
    "9QE6R8cNSQ": "q16",
    "KwgyYPRZkD": "q26",
    "y4yDjqTZjL": "q32",
    "PMdNpyyiFv": "q30",
    "QSneaHYeii": "q25",
    "NobJEWd2f7": "q8",
    "mmqaaS9R3Z": "q27",
    "th5gQmWtDi": "q9",
    "tbeGJ4uq23": "q21",
    "3vTbFPmi5F": "q19"
  }
}
